Workbook

Sheet Clean_Ledger
A1: VAULTSHEET — ZERO-KNOWLEDGE AUDIT LEDGER
A2: Audited source ledger | INR | Red: anomaly | Amber: unverified arithmetic
A3: Opening Balance | C3: Total Debits | E3: Total Credits | G3: Closing Balance | I3: Math Verification % | K3: Hidden Bank Fees | M3: Daily Burn Rate
A4: 1640000 | C4: =SUM(E7:E31) | E4: =SUM(F7:F31) | G4: 1678723.9 | I4: =IFERROR(COUNTIFS(H7:H31,TRUE,A7:A31,"<>")/COUNTA(A7:A31),0) | K4: 1203.6 | M4: 20002.85
A6: tx_id | B6: date | C6: description | D6: ref_no | E6: debit | F6: credit | G6: balance | H6: math_verified | I6: extraction_method | J6: category | K6: tally_ledger | L6: tally_voucher_type | M6: confidence | N6: anomaly_flag | O6: anomaly_reason
A7: 1 | B7: 46031 | C7: UPI/DR/4129195088/TATA STARBUCKS/ICIC0 POS Beverage 2219 | D7: 4129195088 | E7: 8896 | F7: 0 | G7: 1631104 | H7: TRUE | I7: native_grid | J7: Food & Dining | K7: Staff Welfare & Food Exp | L7: Payment | M7: 0.99 | N7: FALSE
A8: 2 | B8: 46090 | C8: NEFT/DR/N261998210/APEX LOGISTICS PVT SBIN0004129/INV-2026-881 FREIGHT CHARG | D8: N261998210 | E8: 59000 | F8: 0 | G8: 1572104 | H8: TRUE | I8: native_grid | J8: Vendor & B2B Transfer | K8: Apex Logistics A/c | L8: Payment | M8: 0.99 | N8: FALSE
A9: 3 | B9: 46090 | C9: NEFT/DR/N262884129/CLOUDHOST INDIA SER HDFC0001209/BILL-OCT-992 DEDICATED SER UNAUTHORIZED BANDWIDTH OVERAGE SURCHAR | D9: N262884129 | E9: 112100 | F9: 0 | G9: 1460004 | H9: TRUE | I9: native_grid | J9: Vendor & B2B Transfer | K9: Cloudhost India A/c | L9: Payment | M9: 0.99 | N9: TRUE | O9: Vendor overcharge vs contract master; Vendor GST rate/math mismatch
A10: 4 | B10: 46090 | C10: NEFT/DR/N263771029/SHARMA PACKAGING IN ICIC0000812/PO-4410 CORRUGATED BOX SUP TAX BILLED AT 18 PCT INSTEAD OF CONTRA | D10: N263771029 | E10: 41300 | F10: 0 | G10: 1418704 | H10: TRUE | I10: native_grid | J10: Vendor & B2B Transfer | K10: Sharma Packaging A/c | L10: Contra | M10: 0.99 | N10: TRUE | O10: Vendor overcharge vs contract master; Vendor GST rate/math mismatch
A11: 5 | B11: 46151 | C11: RTGS/DR/R264991201/METRO POWER INFRAST UTIB0000104/MTHLY DG SET AMNT CONTRACT BRANCH AUTO-SETTLEMENT BATCH MUMBAI MA | D11: R264991201 | E11: 141600 | F11: 0 | G11: 1277104 | H11: TRUE | I11: native_grid | J11: Vendor & B2B Transfer | K11: Metro Power A/c | L11: Contra | M11: 0.99 | N11: TRUE | O11: Statistical high-value outflow outlier
A12: 6 | B12: 46182 | C12: SMS ALERT CHG Q3 | D12: FEE191694 | E12: 17.7 | F12: 0 | G12: 1277086.3 | H12: TRUE | I12: native_grid | J12: Bank Charges & Hidden Fees | K12: Bank Charges A/c | L12: Payment | M12: 0.99 | N12: TRUE | O12: Hidden bank fee / penalty charge
A13: 7 | B13: 46182 | C13: UPI/DR/4129198735/UBER INDIA SYST/ KKBK0000912/Trip Ride 10942/MUMBAI AUTH-REF-66272 VERIFIED | D13: 4129198735 | E13: 7144.75 | F13: 0 | G13: 1269941.6 | H13: TRUE | I13: native_grid | J13: Travel & Commute | K13: Travelling & Conveyance Exp | L13: Payment | M13: 0.99 | N13: FALSE
A14: 8 | B14: 46243 | C14: UPI/DR/4129917245/PHARMEASY HEALTH/YES Med Order 55210 | D14: 4129917245 | E14: 3694.5 | F14: 0 | G14: 1266247.1 | H14: TRUE | I14: native_grid | J14: Shopping & E-Commerce | K14: Office Maintenance & Supplies Exp | L14: Payment | M14: 0.99 | N14: FALSE
A15: 9 | B15: 46304 | C15: UPI/DR/4129819113/UBER INDIA SYST/KKBK Trip Ride 10942 | D15: 4129819113 | E15: 3406.75 | F15: 0 | G15: 1262840.3 | H15: TRUE | I15: native_grid | J15: Travel & Commute | K15: Travelling & Conveyance Exp | L15: Payment | M15: 0.99 | N15: FALSE
A16: 10 | B16: 46304 | C16: IMPS/CR/428519902112 CLIENT RETENTION MILESTONE/ICIC REMARKS: INV SETTLEMENT BATCH 414 | D16: CR643553361 | E16: 0 | F16: 64579 | G16: 1327419.3 | H16: TRUE | I16: native_grid | J16: Salary & Income | K16: Sales & Operating Revenue A/c | L16: Receipt | M16: 0.99 | N16: FALSE
A17: 11 | B17: 46304 | C17: NEFT/CR/N289100441 RAZORPAY SOFTWARE PVT LTD/SETTLEMENT REMARKS: INV SETTLEMENT BATCH 216 | D17: CR567638098 | E17: 0 | F17: 146653 | G17: 1474072.3 | H17: TRUE | I17: native_grid | J17: Salary & Income | K17: Sales & Operating Revenue A/c | L17: Receipt | M17: 0.99 | N17: FALSE
A18: 12 | B18: 46335 | C18: MIN BAL PENALTY | D18: FEE525554 | E18: 590 | F18: 0 | G18: 1473482.3 | H18: TRUE | I18: native_grid | J18: Bank Charges & Hidden Fees | K18: Bank Charges A/c | L18: Payment | M18: 0.99 | N18: TRUE | O18: Hidden bank fee / penalty charge
A19: 13 | B19: 46335 | C19: UPI/DR/428719928311/SWIGGY INSTAMART HDFC0000123/Order 99812/Instant | D19: 428719928311 | E19: 2450 | F19: 0 | G19: 1471032.3 | H19: TRUE | I19: native_grid | J19: Groceries & Quick-Commerce | K19: Office Pantry & Consumables A/c | L19: Payment | M19: 0.99 | N19: FALSE
A20: 14 | B20: 46335 | C20: UPI/DR/428719928311/SWIGGY INSTAMART HDFC0000123/Order 99812/Instant | D20: 428719928311 | E20: 2450 | F20: 0 | G20: 1468582.3 | H20: TRUE | I20: native_grid | J20: Groceries & Quick-Commerce | K20: Office Pantry & Consumables A/c | L20: Payment | M20: 0.99 | N20: TRUE | O20: Duplicate debit charge detected
A21: 15 | B21: 46335 | C21: IMPS CONVENIENCE FEE | D21: FEE103408 | E21: 5.9 | F21: 0 | G21: 1468576.4 | H21: TRUE | I21: native_grid | J21: Bank Charges & Hidden Fees | K21: Bank Charges A/c | L21: Payment | M21: 0.99 | N21: TRUE | O21: Hidden bank fee / penalty charge
A22: 16 | B22: 46335 | C22: UPI/DR/4129783274/UBER INDIA SYST/KKBK Trip Ride 10942 | D22: 4129783274 | E22: 3465.75 | F22: 0 | G22: 1465110.6 | H22: TRUE | I22: native_grid | J22: Travel & Commute | K22: Travelling & Conveyance Exp | L22: Payment | M22: 0.99 | N22: FALSE
A23: 17 | B23: 46278 | C23: INT.PD:01-07-2026 TO 30-09-2026 CREDIT CORP PAYOUT REMARKS: INV SETTLEMENT BATCH 539 | D23: CR381696762 | E23: 0 | F23: 5000 | G23: 1470110.6 | H23: TRUE | I23: native_grid | J23: Salary & Income | K23: Sales & Operating Revenue A/c | L23: Receipt | M23: 0.99 | N23: FALSE
A24: 18 | B24: 46278 | C24: UPI/DR/4129271444/AMAZON PAY INDIA/SBI Marketplace Ref 8812 | D24: 4129271444 | E24: 6901.25 | F24: 0 | G24: 1463209.4 | H24: TRUE | I24: native_grid | J24: Shopping & E-Commerce | K24: Office Maintenance & Supplies Exp | L24: Payment | M24: 0.99 | N24: FALSE
A25: 19 | B25: 46279 | C25: UPI/DR/4129200524/ZOMATO LIMITED/ICIC0 Food Order 77410 | D25: 4129200524 | E25: 1665.25 | F25: 0 | G25: 1461544.1 | H25: TRUE | I25: native_grid | J25: Food & Dining | K25: Staff Welfare & Food Exp | L25: Payment | M25: 0.99 | N25: FALSE
A26: 20 | B26: 46279 | C26: INT.PD:01-07-2026 TO 30-09-2026 CREDIT | D26: CR950063062 | E26: 0 | F26: 5849 | G26: 1467393.1 | H26: TRUE | I26: native_grid | J26: Salary & Income | K26: Sales & Operating Revenue A/c | L26: Receipt | M26: 0.99 | N26: FALSE
A27: 21 | B27: 46281 | C27: ACH/CR/TECHFLOW CLIENT INVOICE 2026-09 | D27: CR663551161 | E27: 0 | F27: 211409 | G27: 1678802.1 | H27: TRUE | I27: native_grid | J27: Salary & Income | K27: Sales & Operating Revenue A/c | L27: Receipt | M27: 0.99 | N27: FALSE
A28: 22 | B28: 46281 | C28: DEBIT CARD ANNUAL FEE | D28: FEE642952 | E28: 590 | F28: 0 | G28: 1678212.1 | H28: TRUE | I28: native_grid | J28: Bank Charges & Hidden Fees | K28: Bank Charges A/c | L28: Payment | M28: 0.99 | N28: TRUE | O28: Hidden bank fee / penalty charge
A29: 23 | B29: 46283 | C29: UPI/DR/4129481886/UBER INDIA SYST/KKBK Trip Ride 10942 | D29: 4129481886 | E29: 1518.75 | F29: 0 | G29: 1676693.4 | H29: TRUE | I29: native_grid | J29: Travel & Commute | K29: Travelling & Conveyance Exp | L29: Payment | M29: 0.99 | N29: FALSE
A30: 24 | B30: 46285 | C30: INT.PD:01-07-2026 TO 30-09-2026 CREDIT | D30: CR948830325 | E30: 0 | F30: 5291 | G30: 1681984.4 | H30: TRUE | I30: native_grid | J30: Salary & Income | K30: Sales & Operating Revenue A/c | L30: Receipt | M30: 0.99 | N30: FALSE
A31: 25 | B31: 46285 | C31: UPI/DR/4129115217/TATA STARBUCKS/ ICIC0000229/POS Beverage 2219/MUMBAI AUTH-REF-85515 VERIFIED | D31: 4129115217 | E31: 3260.5 | F31: 0 | G31: 1678723.9 | H31: TRUE | I31: native_grid | J31: Food & Dining | K31: Staff Welfare & Food Exp | L31: Payment | M31: 0.99 | N31: FALSE

Sheet Executive_Summary
A1: VAULTSHEET — EXECUTIVE SUMMARY
A2: Live Excel formulas | INR | Audit metrics reference the supplied audit snapshot
B5: A | CATEGORY CASH FLOW
B6: Category | C6: Tx Count | D6: Total Spend (Debit) | E6: Total Inflow (Credit) | F6: % of Spend
B7: Revenue | C7: =COUNTIFS('Clean_Ledger'!$J$7:$J$31,SUBSTITUTE(SUBSTITUTE(SUBSTITUTE(B7,"~","~~"),"*","~*"),"?","~?")) | D7: =SUMIFS('Clean_Ledger'!$E$7:$E$31,'Clean_Ledger'!$J$7:$J$31,SUBSTITUTE(SUBSTITUTE(SUBSTITUTE(B7,"~","~~"),"*","~*"),"?","~?")) | E7: =SUMIFS('Clean_Ledger'!$F$7:$F$31,'Clean_Ledger'!$J$7:$J$31,SUBSTITUTE(SUBSTITUTE(SUBSTITUTE(B7,"~","~~"),"*","~*"),"?","~?")) | F7: =IFERROR(D7/SUM('Clean_Ledger'!$E$7:$E$31),0)
B8: Vendor Payments | C8: =COUNTIFS('Clean_Ledger'!$J$7:$J$31,SUBSTITUTE(SUBSTITUTE(SUBSTITUTE(B8,"~","~~"),"*","~*"),"?","~?")) | D8: =SUMIFS('Clean_Ledger'!$E$7:$E$31,'Clean_Ledger'!$J$7:$J$31,SUBSTITUTE(SUBSTITUTE(SUBSTITUTE(B8,"~","~~"),"*","~*"),"?","~?")) | E8: =SUMIFS('Clean_Ledger'!$F$7:$F$31,'Clean_Ledger'!$J$7:$J$31,SUBSTITUTE(SUBSTITUTE(SUBSTITUTE(B8,"~","~~"),"*","~*"),"?","~?")) | F8: =IFERROR(D8/SUM('Clean_Ledger'!$E$7:$E$31),0)
B9: Salaries & Wages | C9: =COUNTIFS('Clean_Ledger'!$J$7:$J$31,SUBSTITUTE(SUBSTITUTE(SUBSTITUTE(B9,"~","~~"),"*","~*"),"?","~?")) | D9: =SUMIFS('Clean_Ledger'!$E$7:$E$31,'Clean_Ledger'!$J$7:$J$31,SUBSTITUTE(SUBSTITUTE(SUBSTITUTE(B9,"~","~~"),"*","~*"),"?","~?")) | E9: =SUMIFS('Clean_Ledger'!$F$7:$F$31,'Clean_Ledger'!$J$7:$J$31,SUBSTITUTE(SUBSTITUTE(SUBSTITUTE(B9,"~","~~"),"*","~*"),"?","~?")) | F9: =IFERROR(D9/SUM('Clean_Ledger'!$E$7:$E$31),0)
B10: Rent | C10: =COUNTIFS('Clean_Ledger'!$J$7:$J$31,SUBSTITUTE(SUBSTITUTE(SUBSTITUTE(B10,"~","~~"),"*","~*"),"?","~?")) | D10: =SUMIFS('Clean_Ledger'!$E$7:$E$31,'Clean_Ledger'!$J$7:$J$31,SUBSTITUTE(SUBSTITUTE(SUBSTITUTE(B10,"~","~~"),"*","~*"),"?","~?")) | E10: =SUMIFS('Clean_Ledger'!$F$7:$F$31,'Clean_Ledger'!$J$7:$J$31,SUBSTITUTE(SUBSTITUTE(SUBSTITUTE(B10,"~","~~"),"*","~*"),"?","~?")) | F10: =IFERROR(D10/SUM('Clean_Ledger'!$E$7:$E$31),0)
B11: Utilities | C11: =COUNTIFS('Clean_Ledger'!$J$7:$J$31,SUBSTITUTE(SUBSTITUTE(SUBSTITUTE(B11,"~","~~"),"*","~*"),"?","~?")) | D11: =SUMIFS('Clean_Ledger'!$E$7:$E$31,'Clean_Ledger'!$J$7:$J$31,SUBSTITUTE(SUBSTITUTE(SUBSTITUTE(B11,"~","~~"),"*","~*"),"?","~?")) | E11: =SUMIFS('Clean_Ledger'!$F$7:$F$31,'Clean_Ledger'!$J$7:$J$31,SUBSTITUTE(SUBSTITUTE(SUBSTITUTE(B11,"~","~~"),"*","~*"),"?","~?")) | F11: =IFERROR(D11/SUM('Clean_Ledger'!$E$7:$E$31),0)
B12: Travel & Entertainment | C12: =COUNTIFS('Clean_Ledger'!$J$7:$J$31,SUBSTITUTE(SUBSTITUTE(SUBSTITUTE(B12,"~","~~"),"*","~*"),"?","~?")) | D12: =SUMIFS('Clean_Ledger'!$E$7:$E$31,'Clean_Ledger'!$J$7:$J$31,SUBSTITUTE(SUBSTITUTE(SUBSTITUTE(B12,"~","~~"),"*","~*"),"?","~?")) | E12: =SUMIFS('Clean_Ledger'!$F$7:$F$31,'Clean_Ledger'!$J$7:$J$31,SUBSTITUTE(SUBSTITUTE(SUBSTITUTE(B12,"~","~~"),"*","~*"),"?","~?")) | F12: =IFERROR(D12/SUM('Clean_Ledger'!$E$7:$E$31),0)
B13: Marketing & Advertising | C13: =COUNTIFS('Clean_Ledger'!$J$7:$J$31,SUBSTITUTE(SUBSTITUTE(SUBSTITUTE(B13,"~","~~"),"*","~*"),"?","~?")) | D13: =SUMIFS('Clean_Ledger'!$E$7:$E$31,'Clean_Ledger'!$J$7:$J$31,SUBSTITUTE(SUBSTITUTE(SUBSTITUTE(B13,"~","~~"),"*","~*"),"?","~?")) | E13: =SUMIFS('Clean_Ledger'!$F$7:$F$31,'Clean_Ledger'!$J$7:$J$31,SUBSTITUTE(SUBSTITUTE(SUBSTITUTE(B13,"~","~~"),"*","~*"),"?","~?")) | F13: =IFERROR(D13/SUM('Clean_Ledger'!$E$7:$E$31),0)
B14: Taxes & Statutory Payments | C14: =COUNTIFS('Clean_Ledger'!$J$7:$J$31,SUBSTITUTE(SUBSTITUTE(SUBSTITUTE(B14,"~","~~"),"*","~*"),"?","~?")) | D14: =SUMIFS('Clean_Ledger'!$E$7:$E$31,'Clean_Ledger'!$J$7:$J$31,SUBSTITUTE(SUBSTITUTE(SUBSTITUTE(B14,"~","~~"),"*","~*"),"?","~?")) | E14: =SUMIFS('Clean_Ledger'!$F$7:$F$31,'Clean_Ledger'!$J$7:$J$31,SUBSTITUTE(SUBSTITUTE(SUBSTITUTE(B14,"~","~~"),"*","~*"),"?","~?")) | F14: =IFERROR(D14/SUM('Clean_Ledger'!$E$7:$E$31),0)
B15: Bank Charges & Fees | C15: =COUNTIFS('Clean_Ledger'!$J$7:$J$31,SUBSTITUTE(SUBSTITUTE(SUBSTITUTE(B15,"~","~~"),"*","~*"),"?","~?")) | D15: =SUMIFS('Clean_Ledger'!$E$7:$E$31,'Clean_Ledger'!$J$7:$J$31,SUBSTITUTE(SUBSTITUTE(SUBSTITUTE(B15,"~","~~"),"*","~*"),"?","~?")) | E15: =SUMIFS('Clean_Ledger'!$F$7:$F$31,'Clean_Ledger'!$J$7:$J$31,SUBSTITUTE(SUBSTITUTE(SUBSTITUTE(B15,"~","~~"),"*","~*"),"?","~?")) | F15: =IFERROR(D15/SUM('Clean_Ledger'!$E$7:$E$31),0)
B16: Transfers | C16: =COUNTIFS('Clean_Ledger'!$J$7:$J$31,SUBSTITUTE(SUBSTITUTE(SUBSTITUTE(B16,"~","~~"),"*","~*"),"?","~?")) | D16: =SUMIFS('Clean_Ledger'!$E$7:$E$31,'Clean_Ledger'!$J$7:$J$31,SUBSTITUTE(SUBSTITUTE(SUBSTITUTE(B16,"~","~~"),"*","~*"),"?","~?")) | E16: =SUMIFS('Clean_Ledger'!$F$7:$F$31,'Clean_Ledger'!$J$7:$J$31,SUBSTITUTE(SUBSTITUTE(SUBSTITUTE(B16,"~","~~"),"*","~*"),"?","~?")) | F16: =IFERROR(D16/SUM('Clean_Ledger'!$E$7:$E$31),0)
B17: Other | C17: =COUNTIFS('Clean_Ledger'!$J$7:$J$31,SUBSTITUTE(SUBSTITUTE(SUBSTITUTE(B17,"~","~~"),"*","~*"),"?","~?")) | D17: =SUMIFS('Clean_Ledger'!$E$7:$E$31,'Clean_Ledger'!$J$7:$J$31,SUBSTITUTE(SUBSTITUTE(SUBSTITUTE(B17,"~","~~"),"*","~*"),"?","~?")) | E17: =SUMIFS('Clean_Ledger'!$F$7:$F$31,'Clean_Ledger'!$J$7:$J$31,SUBSTITUTE(SUBSTITUTE(SUBSTITUTE(B17,"~","~~"),"*","~*"),"?","~?")) | F17: =IFERROR(D17/SUM('Clean_Ledger'!$E$7:$E$31),0)
B18: Bank Charges & Hidden Fees | C18: =COUNTIFS('Clean_Ledger'!$J$7:$J$31,SUBSTITUTE(SUBSTITUTE(SUBSTITUTE(B18,"~","~~"),"*","~*"),"?","~?")) | D18: =SUMIFS('Clean_Ledger'!$E$7:$E$31,'Clean_Ledger'!$J$7:$J$31,SUBSTITUTE(SUBSTITUTE(SUBSTITUTE(B18,"~","~~"),"*","~*"),"?","~?")) | E18: =SUMIFS('Clean_Ledger'!$F$7:$F$31,'Clean_Ledger'!$J$7:$J$31,SUBSTITUTE(SUBSTITUTE(SUBSTITUTE(B18,"~","~~"),"*","~*"),"?","~?")) | F18: =IFERROR(D18/SUM('Clean_Ledger'!$E$7:$E$31),0)
... B24: Vendor & B2B Transfer | C24: =COUNTIFS('Clean_Ledger'!$J$7:$J$31,SUBSTITUTE(SUBSTITUTE(SUBSTITUTE(B24,"~","~~"),"*","~*"),"?","~?")) | D24: =SUMIFS('Clean_Ledger'!$E$7:$E$31,'Clean_Ledger'!$J$7:$J$31,SUBSTITUTE(SUBSTITUTE(SUBSTITUTE(B24,"~","~~"),"*","~*"),"?","~?")) | E24: =SUMIFS('Clean_Ledger'!$F$7:$F$31,'Clean_Ledger'!$J$7:$J$31,SUBSTITUTE(SUBSTITUTE(SUBSTITUTE(B24,"~","~~"),"*","~*"),"?","~?")) | F24: =IFERROR(D24/SUM('Clean_Ledger'!$E$7:$E$31),0)
B25: TOTAL | C25: =SUM(C7:C24) | D25: =SUM(D7:D24) | E25: =SUM(E7:E24) | F25: =SUM(F7:F24)
B28: B | TOP EXPENSE INSPECTOR
B29: Largest Single Debit Outflow | C29: =MAX('Clean_Ledger'!$E$7:$E$31)
B30: Exact Narration | C30: =IF(C29<=0,"None",_xlfn.XLOOKUP(C29,'Clean_Ledger'!$E$7:$E$31,'Clean_Ledger'!$C$7:$C$31,"None",0))
B31: Transaction Date | C31: =IF(C29<=0,"None",_xlfn.XLOOKUP(C29,'Clean_Ledger'!$E$7:$E$31,'Clean_Ledger'!$B$7:$B$31,"None",0))
B32: Equal largest debits: the first transaction in source order is shown.
B35: C | BURN RATE, HIDDEN FEES & MATHEMATICAL RECONCILIATION
B36: Daily Burn Rate | C36: ='Clean_Ledger'!M4
B37: Estimated Cash Runway (Days) | C37: =IF(C36>0,MAX(0,'Clean_Ledger'!G4)/C36,"N/A")
B38: Total Hidden Bank Fees | C38: ='Clean_Ledger'!K4
B39: Opening Balance | C39: ='Clean_Ledger'!A4
B40: Total Credits | C40: =SUM('Clean_Ledger'!$F$7:$F$31)
B41: Total Debits | C41: =SUM('Clean_Ledger'!$E$7:$E$31)
B42: Closing Balance | C42: ='Clean_Ledger'!G4
B43: Net Cash Flow | C43: =SUM('Clean_Ledger'!$F$7:$F$31)-SUM('Clean_Ledger'!$E$7:$E$31)
B44: Reconciliation Difference | C44: =(C39+C40-C41)-C42
B45: Mathematical Reconciliation | C45: =IF(ABS((C39+C40-C41)-C42)<0.01,"RECONCILED (0.00 DIFF)","DISCREPANCY DETECTED")
B47: Transaction Count | C47: =COUNTIFS('Clean_Ledger'!$A$7:$A$31,"<>")
B48: Math Verification % | C48: =IFERROR(COUNTIFS('Clean_Ledger'!$H$7:$H$31,TRUE,'Clean_Ledger'!$A$7:$A$31,"<>")/COUNTIFS('Clean_Ledger'!$A$7:$A$31,"<>"),0)
B49: Unverified Transactions | C49: =COUNTIFS('Clean_Ledger'!$H$7:$H$31,FALSE,'Clean_Ledger'!$A$7:$A$31,"<>")
B50: Flagged Anomalies | C50: =COUNTIFS('Clean_Ledger'!$N$7:$N$31,TRUE,'Clean_Ledger'!$A$7:$A$31,"<>")
B52: Runway = nonnegative closing cash / supplied daily burn; N/A when burn is zero or negative. Hidden fees and burn are audit inputs.

Sheet Risk_And_Anomalies
A1: VAULTSHEET — RISK & ANOMALIES
A2: Audit exceptions snapshot | Enter review decisions and sign-off in the yellow column
A4: 8 transactions require review | Regenerate this tab after changing source audit flags.
A6: tx_id | B6: date | C6: description | D6: ref_no | E6: debit | F6: credit | G6: balance | H6: math_verified | I6: extraction_method | J6: category | K6: tally_ledger | L6: tally_voucher_type | M6: confidence | N6: anomaly_flag | O6: anomaly_reason | P6: Chartered Accountant / Auditor Remarks
A7: 3 | B7: 46090 | C7: NEFT/DR/N262884129/CLOUDHOST INDIA SER HDFC0001209/BILL-OCT-992 DEDICATED SER UNAUTHORIZED BANDWIDTH OVERAGE SURCHAR | D7: N262884129 | E7: 112100 | F7: 0 | G7: 1460004 | H7: TRUE | I7: native_grid | J7: Vendor & B2B Transfer | K7: Cloudhost India A/c | L7: Payment | M7: 0.99 | N7: TRUE | O7: Vendor overcharge vs contract master; Vendor GST rate/math mismatch
A8: 4 | B8: 46090 | C8: NEFT/DR/N263771029/SHARMA PACKAGING IN ICIC0000812/PO-4410 CORRUGATED BOX SUP TAX BILLED AT 18 PCT INSTEAD OF CONTRA | D8: N263771029 | E8: 41300 | F8: 0 | G8: 1418704 | H8: TRUE | I8: native_grid | J8: Vendor & B2B Transfer | K8: Sharma Packaging A/c | L8: Contra | M8: 0.99 | N8: TRUE | O8: Vendor overcharge vs contract master; Vendor GST rate/math mismatch
A9: 5 | B9: 46151 | C9: RTGS/DR/R264991201/METRO POWER INFRAST UTIB0000104/MTHLY DG SET AMNT CONTRACT BRANCH AUTO-SETTLEMENT BATCH MUMBAI MA | D9: R264991201 | E9: 141600 | F9: 0 | G9: 1277104 | H9: TRUE | I9: native_grid | J9: Vendor & B2B Transfer | K9: Metro Power A/c | L9: Contra | M9: 0.99 | N9: TRUE | O9: Statistical high-value outflow outlier
A10: 6 | B10: 46182 | C10: SMS ALERT CHG Q3 | D10: FEE191694 | E10: 17.7 | F10: 0 | G10: 1277086.3 | H10: TRUE | I10: native_grid | J10: Bank Charges & Hidden Fees | K10: Bank Charges A/c | L10: Payment | M10: 0.99 | N10: TRUE | O10: Hidden bank fee / penalty charge
A11: 12 | B11: 46335 | C11: MIN BAL PENALTY | D11: FEE525554 | E11: 590 | F11: 0 | G11: 1473482.3 | H11: TRUE | I11: native_grid | J11: Bank Charges & Hidden Fees | K11: Bank Charges A/c | L11: Payment | M11: 0.99 | N11: TRUE | O11: Hidden bank fee / penalty charge
A12: 14 | B12: 46335 | C12: UPI/DR/428719928311/SWIGGY INSTAMART HDFC0000123/Order 99812/Instant | D12: 428719928311 | E12: 2450 | F12: 0 | G12: 1468582.3 | H12: TRUE | I12: native_grid | J12: Groceries & Quick-Commerce | K12: Office Pantry & Consumables A/c | L12: Payment | M12: 0.99 | N12: TRUE | O12: Duplicate debit charge detected
A13: 15 | B13: 46335 | C13: IMPS CONVENIENCE FEE | D13: FEE103408 | E13: 5.9 | F13: 0 | G13: 1468576.4 | H13: TRUE | I13: native_grid | J13: Bank Charges & Hidden Fees | K13: Bank Charges A/c | L13: Payment | M13: 0.99 | N13: TRUE | O13: Hidden bank fee / penalty charge
A14: 22 | B14: 46281 | C14: DEBIT CARD ANNUAL FEE | D14: FEE642952 | E14: 590 | F14: 0 | G14: 1678212.1 | H14: TRUE | I14: native_grid | J14: Bank Charges & Hidden Fees | K14: Bank Charges A/c | L14: Payment | M14: 0.99 | N14: TRUE | O14: Hidden bank fee / penalty charge

Sheet Tally_Prime_Import
A1: VAULTSHEET — TALLYPRIME VOUCHER IMPORT
A2: Map row 6 as headers and row 7 onward as data | Use ledger names configured in the destination company
A6: Date (DD-MM-YYYY) | B6: Voucher Type | C6: Party / Ledger Name | D6: Bank Ledger Name | E6: Instrument / UTR No | F6: Debit Amount | G6: Credit Amount | H6: Narration
A7: 09-01-2026 | B7: Payment | C7: Staff Welfare & Food Exp | D7: Primary Bank A/c | E7: 4129195088 | F7: 8896 | G7: 0 | H7: UPI/DR/4129195088/TATA STARBUCKS/ICIC0 POS Beverage 2219
A8: 09-03-2026 | B8: Payment | C8: Apex Logistics A/c | D8: Primary Bank A/c | E8: N261998210 | F8: 59000 | G8: 0 | H8: NEFT/DR/N261998210/APEX LOGISTICS PVT SBIN0004129/INV-2026-881 FREIGHT CHARG
A9: 09-03-2026 | B9: Payment | C9: Cloudhost India A/c | D9: Primary Bank A/c | E9: N262884129 | F9: 112100 | G9: 0 | H9: NEFT/DR/N262884129/CLOUDHOST INDIA SER HDFC0001209/BILL-OCT-992 DEDICATED SER UNAUTHORIZED BANDWIDTH OVERAGE SURCHAR
A10: 09-03-2026 | B10: Contra | C10: Sharma Packaging A/c | D10: Primary Bank A/c | E10: N263771029 | F10: 41300 | G10: 0 | H10: NEFT/DR/N263771029/SHARMA PACKAGING IN ICIC0000812/PO-4410 CORRUGATED BOX SUP TAX BILLED AT 18 PCT INSTEAD OF CONTRA
A11: 09-05-2026 | B11: Contra | C11: Metro Power A/c | D11: Primary Bank A/c | E11: R264991201 | F11: 141600 | G11: 0 | H11: RTGS/DR/R264991201/METRO POWER INFRAST UTIB0000104/MTHLY DG SET AMNT CONTRACT BRANCH AUTO-SETTLEMENT BATCH MUMBAI MA
A12: 09-06-2026 | B12: Payment | C12: Bank Charges A/c | D12: Primary Bank A/c | E12: FEE191694 | F12: 17.7 | G12: 0 | H12: SMS ALERT CHG Q3
A13: 09-06-2026 | B13: Payment | C13: Travelling & Conveyance Exp | D13: Primary Bank A/c | E13: 4129198735 | F13: 7144.75 | G13: 0 | H13: UPI/DR/4129198735/UBER INDIA SYST/ KKBK0000912/Trip Ride 10942/MUMBAI AUTH-REF-66272 VERIFIED
A14: 09-08-2026 | B14: Payment | C14: Office Maintenance & Supplies Exp | D14: Primary Bank A/c | E14: 4129917245 | F14: 3694.5 | G14: 0 | H14: UPI/DR/4129917245/PHARMEASY HEALTH/YES Med Order 55210
A15: 09-10-2026 | B15: Payment | C15: Travelling & Conveyance Exp | D15: Primary Bank A/c | E15: 4129819113 | F15: 3406.75 | G15: 0 | H15: UPI/DR/4129819113/UBER INDIA SYST/KKBK Trip Ride 10942
A16: 09-10-2026 | B16: Receipt | C16: Sales & Operating Revenue A/c | D16: Primary Bank A/c | E16: CR643553361 | F16: 0 | G16: 64579 | H16: IMPS/CR/428519902112 CLIENT RETENTION MILESTONE/ICIC REMARKS: INV SETTLEMENT BATCH 414
A17: 09-10-2026 | B17: Receipt | C17: Sales & Operating Revenue A/c | D17: Primary Bank A/c | E17: CR567638098 | F17: 0 | G17: 146653 | H17: NEFT/CR/N289100441 RAZORPAY SOFTWARE PVT LTD/SETTLEMENT REMARKS: INV SETTLEMENT BATCH 216
A18: 09-11-2026 | B18: Payment | C18: Bank Charges A/c | D18: Primary Bank A/c | E18: FEE525554 | F18: 590 | G18: 0 | H18: MIN BAL PENALTY
... A31: 20-09-2026 | B31: Payment | C31: Staff Welfare & Food Exp | D31: Primary Bank A/c | E31: 4129115217 | F31: 3260.5 | G31: 0 | H31: UPI/DR/4129115217/TATA STARBUCKS/ ICIC0000229/POS Beverage 2219/MUMBAI AUTH-REF-85515 VERIFIED
